CTkMenuBarPlus/_CDMOptionButton.py
CTkMenuBarPlus/_CDMSubmenuButton.py
CTkMenuBarPlus/__init__.py
CTkMenuBarPlus/accelerators.py
CTkMenuBarPlus/constants.py
CTkMenuBarPlus/context_menu.py
CTkMenuBarPlus/custom_exception_classes.py
CTkMenuBarPlus/dropdown_menu.py
CTkMenuBarPlus/menu_bar.py
CTkMenuBarPlus/title_menu_win.py
ctkmenubarplus-1.3.dist-info/licenses/LICENSE
ctkmenubarplus-1.3.dist-info/METADATA
ctkmenubarplus-1.3.dist-info/WHEEL
ctkmenubarplus-1.3.dist-info/top_level.txt
ctkmenubarplus-1.3.dist-info/RECORD
