Metadata-Version: 2.4
Name: CTkMenuBarPlus
Version: 1.3
Summary: Modern menu bar widget library for customtkinter with enhanced features
Author-email: xzyqox <xzyqox@gmail.com>
Maintainer-email: xzyqox <xzyqox@gmail.com>
License: MIT License
Project-URL: Homepage, https://github.com/KiTant/CTkMenuBarPlus
Project-URL: Repository, https://github.com/KiTant/CTkMenuBarPlus
Project-URL: Issues, https://github.com/KiTant/CTkMenuBarPlus/issues
Project-URL: Documentation, https://github.com/KiTant/CTkMenuBarPlus#readme
Keywords: customtkinter,menu,menubar,dropdown,gui,tkinter,accelerators,context-menu
Classifier: Intended Audience :: Developers
Classifier: License :: OSI Approved :: MIT License
Classifier: Operating System :: OS Independent
Classifier: Programming Language :: Python :: 3
Classifier: Programming Language :: Python :: 3.8
Classifier: Programming Language :: Python :: 3.9
Classifier: Programming Language :: Python :: 3.10
Classifier: Programming Language :: Python :: 3.11
Classifier: Programming Language :: Python :: 3.12
Classifier: Programming Language :: Python :: 3.13
Classifier: Topic :: Software Development :: Libraries :: Python Modules
Classifier: Topic :: Software Development :: User Interfaces
Requires-Python: >=3.8
License-File: LICENSE
Requires-Dist: customtkinter>=5.0.0
Requires-Dist: Pillow>=8.0.0
Provides-Extra: dev
Requires-Dist: pytest>=6.0; extra == "dev"
Requires-Dist: black; extra == "dev"
Requires-Dist: flake8; extra == "dev"
Dynamic: license-file
